{
  "attempts": [
    {
      "log": "/mnt/infini-data/test/BeyondMimic/logs/tracking_official_replay_conversion/csv_to_npz_local_20260618_175634.log",
      "markers": {
        "argparse_enable_cameras_false_error": true,
        "cuda_visible_devices_ordinal_error": false,
        "libglu_missing": false,
        "motion_saved": false,
        "no_contact_sensors": false,
        "p2p_iommu_warning": false,
        "robot_reference_unresolved": false,
        "rsl_rl_env_missing": false,
        "timeout_or_killed": false,
        "traceback": false,
        "usd_save_not_allowed": false
      },
      "return_code_recorded": 2,
      "size_bytes": 678
    },
    {
      "log": "/mnt/infini-data/test/BeyondMimic/logs/tracking_official_replay_conversion/csv_to_npz_local_20260618_175702.log",
      "markers": {
        "argparse_enable_cameras_false_error": false,
        "cuda_visible_devices_ordinal_error": true,
        "libglu_missing": false,
        "motion_saved": false,
        "no_contact_sensors": false,
        "p2p_iommu_warning": true,
        "robot_reference_unresolved": false,
        "rsl_rl_env_missing": true,
        "timeout_or_killed": false,
        "traceback": true,
        "usd_save_not_allowed": false
      },
      "return_code_recorded": null,
      "size_bytes": 13403
    },
    {
      "log": "/mnt/infini-data/test/BeyondMimic/logs/tracking_official_replay_conversion/csv_to_npz_local_20260618_180559_no_cvd.log",
      "markers": {
        "argparse_enable_cameras_false_error": false,
        "cuda_visible_devices_ordinal_error": false,
        "libglu_missing": true,
        "motion_saved": false,
        "no_contact_sensors": true,
        "p2p_iommu_warning": true,
        "robot_reference_unresolved": true,
        "rsl_rl_env_missing": false,
        "timeout_or_killed": false,
        "traceback": true,
        "usd_save_not_allowed": true
      },
      "return_code_recorded": null,
      "size_bytes": 24612
    },
    {
      "log": "/mnt/infini-data/test/BeyondMimic/logs/tracking_official_replay_conversion/csv_to_npz_local_20260618_180844_project_usd.log",
      "markers": {
        "argparse_enable_cameras_false_error": false,
        "cuda_visible_devices_ordinal_error": false,
        "libglu_missing": true,
        "motion_saved": false,
        "no_contact_sensors": true,
        "p2p_iommu_warning": true,
        "robot_reference_unresolved": true,
        "rsl_rl_env_missing": false,
        "timeout_or_killed": false,
        "traceback": true,
        "usd_save_not_allowed": true
      },
      "return_code_recorded": null,
      "size_bytes": 24948
    },
    {
      "log": "/mnt/infini-data/test/BeyondMimic/logs/tracking_official_replay_conversion/csv_to_npz_local_20260618_181148_libglu.log",
      "markers": {
        "argparse_enable_cameras_false_error": false,
        "cuda_visible_devices_ordinal_error": false,
        "libglu_missing": false,
        "motion_saved": false,
        "no_contact_sensors": true,
        "p2p_iommu_warning": true,
        "robot_reference_unresolved": true,
        "rsl_rl_env_missing": false,
        "timeout_or_killed": false,
        "traceback": true,
        "usd_save_not_allowed": true
      },
      "return_code_recorded": null,
      "size_bytes": 24560
    },
    {
      "log": "/mnt/infini-data/test/BeyondMimic/logs/tracking_official_replay_conversion/csv_to_npz_local_20260618_181419_chmod_patch.log",
      "markers": {
        "argparse_enable_cameras_false_error": false,
        "cuda_visible_devices_ordinal_error": false,
        "libglu_missing": false,
        "motion_saved": false,
        "no_contact_sensors": true,
        "p2p_iommu_warning": true,
        "robot_reference_unresolved": true,
        "rsl_rl_env_missing": false,
        "timeout_or_killed": false,
        "traceback": true,
        "usd_save_not_allowed": true
      },
      "return_code_recorded": null,
      "size_bytes": 24560
    }
  ],
  "checks": {
    "attempt_logs_present": true,
    "basic_usd_stage_save_failure_recorded": true,
    "does_not_claim_replay_success": true,
    "does_not_start_training": true,
    "local_csv_to_npz_script_exists": true,
    "mjcf_bypass_blocked_recorded": true,
    "mjcf_stage_probe_recorded": true,
    "motion_npz_contract_written": false,
    "motion_npz_written": false,
    "rsl_rl_env_import_ok": true,
    "rsl_rl_isaaclab_expected_version_installed": true,
    "rsl_rl_missing_was_repaired": true,
    "system_libglu_available": true,
    "tracking_pip_check_ok": true,
    "urdf_conversion_probe_recorded": true,
    "urdf_converter_empty_usd_recorded": true,
    "urdf_path_tiny_probe_recorded": true,
    "urdf_save_forbidden_and_vulkan_device_lost_recorded": true,
    "usd_save_blocker_recorded": true
  },
  "contract_json": "/mnt/infini-data/test/BeyondMimic/res/tracking/official_replay_conversion/walk1_subject1_frames_1_180_motion_contract.json",
  "environment_repairs": {
    "libglu": "=============================\u7b97\u529b\u725b=============================\n\u6b22\u8fce\u4f7f\u7528\u4e00\u7ad9\u5f0fAI\u5e73\u53f0\u5f00\u53d1\u673a\u670d\u52a1\uff01\n\u2550\u2550\u2550\u2550\u2550\u2550\u2550\u2550\u2550\u2550\u2550\u2550\u2550\u2550\u2550\u2550\u2550\u2550\u2550\u2550\u2550\u2550\u2550\u2550\u2550\u2550\u2550\u2550\u2550\u2550\u2550\u2550\u2550\u2550\u2550\nPATH                \u7c7b\u578b    \n/                   \u7cfb\u7edf\u76d8(\u4e0a\u9650100G)\n/mnt/infini-data    \u5171\u4eab\u9ad8\u6027\u80fd\u5b58\u50a8\n\u2550\u2550\u2550\u2550\u2550\u2550\u2550\u2550\u2550\u2550\u2550\u2550\u2550\u2550\u2550\u2550\u2550\u2550\u2550\u2550\u2550\u2550\u2550\u2550\u2550\u2550\u2550\u2550\u2550\u2550\u2550\u2550\u2550\u2550\u2550\n\u001b[38;5;46m1. \u6211\u4eec\u4f1a\u5728\u60a8\u505c\u6b62\u5f00\u53d1\u673a\u65f6\u5bf9\u7cfb\u7edf\u76d8\u7684\u5185\u5bb9\uff08\u4e0d\u5305\u62ec /tmp \u76ee\u5f55\uff09\u8fdb\u884c\u6301\u4e45\u5316\u4fdd\u5b58\uff0c\u91cd\u65b0\u542f\u52a8\u65f6\u4f1a\u8fdb\u884c\u6062\u590d\u3002\u001b[0m\n\u001b[38;5;46m2. \u5982\u9700\u5728\u5f00\u53d1\u673a\u5185\u90e8\u4f7f\u7528 Docker\uff0c\u5fc5\u987b\u5728\u521b\u5efa\u65f6\u52fe\u9009 \u201cdocker\u5bb9\u5668\u201d\u3002\u5185\u90e8\u5bb9\u5668\u53ef\u4f7f\u7528\u5171\u4eab\u5f00\u53d1\u673a\u5168\u90e8\u663e\u5361\u8d44\u6e90\uff0c\u5e76\u6302\u8f7d\u5b58\u50a8\uff1adocker run --gpus=all -v /mnt:/mnt <image>\u001b[0m\n\u001b[38;5;46m3. \u4f7f\u7528 docker \u5bb9\u5668 push \u955c\u50cf\u7684\u5730\u5740\u4e3a\uff1acr.infini-ai.com/te-dcsfqwzi4dg6rqsg\u001b[0m\n\u001b[38;5;46m4. \u672c\u5730\u5b58\u50a8\u4f1a\u968f\u7740\u5f00\u53d1\u673a\u5173\u673a/\u5220\u9664\u800c\u88ab\u9500\u6bc1\uff0c\u82e5\u9700\u6301\u4e45\u5316\u5b58\u50a8\uff0c\u8bf7\u53ca\u65f6\u5c06\u6570\u636e\u4fdd\u5b58\u8fdb\u7cfb\u7edf\u76d8\u6216\u5171\u4eab\u9ad8\u6027\u80fd\u5b58\u50a8\u3002\u001b[0m\n===================================================================\n\tlibGLU.so.1 (libc6,x86-64) => /lib/x86_64-linux-gnu/libGLU.so.1",
    "notes": [
      "Installed rsl-rl-lib==2.3.1 in bm_tracking without changing torch 2.5.1+cu121.",
      "Installed host libglu1-mesa so Isaac Sim can resolve libGLU.so.1.",
      "Removed CUDA_VISIBLE_DEVICES from Isaac conversion command to avoid Omniverse/CUDA ordinal mismatch."
    ],
    "pip_check": "No broken requirements found.",
    "rsl_rl": "2.5.1+cu121\n/mnt/infini-data/test/BeyondMimic/envs/bm_tracking/lib/python3.10/site-packages/rsl_rl/__init__.py"
  },
  "experiment_type": "tracking_official_replay_conversion_audit",
  "generated_at": "2026-06-18T11:05:14.172759+00:00",
  "interpretation": {
    "goal_complete": false,
    "next_action": "Investigate why Kit/USD marks project-local layers as not saveable in this headless run. A valid basic USD stage save must pass before retrying URDF/MJCF conversion or csv_to_npz.",
    "why_not_complete": "The conversion progressed beyond argument parsing, RSL-RL import, CUDA ordinal, and libGLU issues, but the isolated G1 URDF conversion probe produces a tiny USD with no default prim, no traversable robot prims, and no rigid-body-like prims. The path/tiny contrast probe further records project-local USD layer save-forbidden errors followed by Vulkan device loss before a valid URDF conversion payload. The MJCF/stage bypass probe shows the same save policy at the basic USD stage-save layer, so the current blocker is below URDF-vs-MJCF asset format. No valid official motion.npz or replay has been produced."
  },
  "latest_blocker": "mjcf_or_stage_usd_save_forbidden_and_vulkan_device_lost",
  "mjcf_stage_probe_json": "/mnt/infini-data/test/BeyondMimic/res/tracking/mjcf_stage_probe/tracking_mjcf_stage_probe.json",
  "mjcf_stage_probe_summary": {
    "checks": {
      "all_g1_mjcf_mesh_refs_resolve_statically": true,
      "app_launcher_closed_or_timeout_recorded": true,
      "app_launcher_payload_or_blocker_recorded": true,
      "app_launcher_reached_after_app": true,
      "does_not_claim_motion_npz": true,
      "does_not_start_replay_or_training": true,
      "g1_mjcf_conversion_success": false,
      "g1_mjcf_exists": true,
      "libglu_missing_absent": true,
      "minimal_stage_save_success": false,
      "project_egl_icd_exists": true,
      "tiny_mjcf_conversion_success": false,
      "tracking_python_exists": true
    },
    "current_blocker": "mjcf_or_stage_usd_save_forbidden_and_vulkan_device_lost",
    "markers": {
      "libglu_missing": false,
      "p2p_iommu_warning": true,
      "sentinel_after_app": true,
      "sentinel_after_close": false,
      "sentinel_payload": true,
      "timed_out": true,
      "traceback": false,
      "usd_save_not_allowed": true,
      "vulkan_device_lost": true
    },
    "returncode": 124,
    "status": "ok_with_blocker_classified"
  },
  "motion_npz": "/mnt/infini-data/test/BeyondMimic/res/tracking/official_replay_conversion/walk1_subject1_frames_1_180_motion.npz",
  "outputs": {
    "json": "/mnt/infini-data/test/BeyondMimic/res/tracking/official_replay_conversion/tracking_official_replay_conversion_audit.json"
  },
  "scope": "Bounded local execution attempts for official-equivalent whole_body_tracking csv_to_npz conversion. No replay video, PPO training, policy evaluation, DAgger, VAE, or diffusion closed-loop run is claimed.",
  "selected_motion": "/mnt/infini-data/test/BeyondMimic/download/official/LAFAN1_Retargeting_Dataset/g1/walk1_subject1.csv",
  "status": "ok_with_blocked_conversion",
  "urdf_conversion_probe_json": "/mnt/infini-data/test/BeyondMimic/res/tracking/urdf_conversion_probe/tracking_urdf_conversion_probe.json",
  "urdf_conversion_probe_summary": {
    "converter_usd_mode": "0o567",
    "converter_usd_size": 492,
    "default_prim_valid": false,
    "prim_count": 0,
    "returncode": -11,
    "rigid_body_like_count": 0,
    "stage_open_ok": true,
    "status": "ok_with_urdf_usd_blocker"
  },
  "urdf_path_tiny_probe_json": "/mnt/infini-data/test/BeyondMimic/res/tracking/urdf_path_tiny_probe/tracking_urdf_path_tiny_probe.json",
  "urdf_path_tiny_probe_summary": {
    "checks": {
      "all_g1_package_mesh_refs_resolve_statically": true,
      "app_launcher_closed": false,
      "app_launcher_reached_payload": false,
      "does_not_claim_motion_npz": true,
      "does_not_start_replay_or_training": true,
      "g1_abs_empty_usd_recorded": false,
      "g1_abs_mesh_conversion_success": false,
      "g1_original_conversion_success": false,
      "g1_original_empty_usd_recorded": false,
      "g1_urdf_exists": true,
      "libglu_missing_absent": true,
      "project_egl_icd_exists": true,
      "tiny_urdf_conversion_success": false,
      "tracking_python_exists": true
    },
    "current_blocker": "usd_layer_save_forbidden_and_vulkan_device_lost_before_payload",
    "markers": {
      "libglu_missing": false,
      "p2p_iommu_warning": true,
      "segmentation_fault": false,
      "sentinel_after_app": true,
      "sentinel_after_close": false,
      "sentinel_payload": false,
      "timed_out": true,
      "traceback": false,
      "usd_save_not_allowed": true,
      "vulkan_device_lost": true
    },
    "returncode": 124,
    "status": "ok_with_blocker_classified"
  }
}